thoughts/__init__.py
thoughts/context.py
thoughts/rules_engine.py
thoughts/unification.py
thoughts/commands/__init__.py
thoughts/commands/load_json.py
thoughts/commands/lookup.py
thoughts/commands/output.py
thoughts/commands/prompt.py
thoughts/commands/random.py
thoughts/commands/read_rss.py
thoughts/commands/replace.py
thoughts/commands/save_json.py
thoughts/commands/store.py
thoughts/commands/tokenize.py
thoughts-0.1.6.dist-info/LICENSE
thoughts-0.1.6.dist-info/METADATA
thoughts-0.1.6.dist-info/WHEEL
thoughts-0.1.6.dist-info/top_level.txt
thoughts-0.1.6.dist-info/RECORD
