Metadata-Version: 2.1
Name: thoughts
Version: 0.1.6
Summary: Thoughts is a lightweight rules engine
Home-page: https://github.com/hofmanniac/thoughts
Author: Jeremy Hofmann (Hofmanniac)
Author-email: jeremy.lee.hofmann@gmail.com
License: MIT
Platform: UNKNOWN
Classifier: License :: OSI Approved :: MIT License
Classifier: Programming Language :: Python :: 3
Classifier: Programming Language :: Python :: 3.7
Requires-Dist: feedparser
